[
  {"draft_player_id":"KVL-P-DRAFT-SKKU-001","proposed_player_id":"KVL-P-000017","display_code":null,"name_ko":"권준범","birth_date":null,"review_status":"needs_review"},
  {"draft_player_id":"KVL-P-DRAFT-SKKU-002","proposed_player_id":"KVL-P-000018","display_code":null,"name_ko":"신명호","birth_date":null,"review_status":"needs_review"},
  {"draft_player_id":"KVL-P-DRAFT-SKKU-003","proposed_player_id":"KVL-P-000019","display_code":null,"name_ko":"송대영","birth_date":null,"review_status":"needs_review"},
  {"draft_player_id":"KVL-P-DRAFT-SKKU-004","proposed_player_id":"KVL-P-000020","display_code":null,"name_ko":"한승우","birth_date":null,"review_status":"needs_review"},
  {"draft_player_id":"KVL-P-DRAFT-SKKU-005","proposed_player_id":"KVL-P-000021","display_code":null,"name_ko":"전현태","birth_date":null,"review_status":"needs_review"},
  {"draft_player_id":"KVL-P-DRAFT-SKKU-006","proposed_player_id":"KVL-P-000022","display_code":null,"name_ko":"김정식","birth_date":null,"review_status":"needs_review"},
  {"draft_player_id":"KVL-P-DRAFT-SKKU-007","proposed_player_id":"KVL-P-000023","display_code":null,"name_ko":"최보민","birth_date":null,"review_status":"needs_review"},
  {"draft_player_id":"KVL-P-DRAFT-SKKU-008","proposed_player_id":"KVL-P-000024","display_code":null,"name_ko":"강환승","birth_date":null,"review_status":"needs_review"},
  {"draft_player_id":"KVL-P-DRAFT-SKKU-009","proposed_player_id":"KVL-P-000025","display_code":null,"name_ko":"김대환","birth_date":null,"review_status":"needs_review"},
  {"draft_player_id":"KVL-P-DRAFT-SKKU-010","proposed_player_id":"KVL-P-000026","display_code":null,"name_ko":"원태호","birth_date":null,"review_status":"needs_review"},
  {"draft_player_id":"KVL-P-DRAFT-SKKU-011","proposed_player_id":"KVL-P-000027","display_code":null,"name_ko":"백승현","birth_date":null,"review_status":"needs_review"},
  {"draft_player_id":"KVL-P-DRAFT-SKKU-012","proposed_player_id":"KVL-P-000028","display_code":null,"name_ko":"박태민","birth_date":null,"review_status":"needs_review"},
  {"draft_player_id":"KVL-P-DRAFT-SKKU-013","proposed_player_id":"KVL-P-000029","display_code":null,"name_ko":"김도윤","birth_date":null,"review_status":"needs_review"},
  {"draft_player_id":"KVL-P-DRAFT-SKKU-014","proposed_player_id":"KVL-P-000030","display_code":null,"name_ko":"김남범","birth_date":null,"review_status":"needs_review"},
  {"draft_player_id":"KVL-P-DRAFT-SKKU-015","proposed_player_id":"KVL-P-000031","display_code":null,"name_ko":"김동균","birth_date":null,"review_status":"needs_review"},
  {"draft_player_id":"KVL-P-DRAFT-SKKU-016","proposed_player_id":"KVL-P-000032","display_code":null,"name_ko":"최준영","birth_date":null,"review_status":"needs_review"}
]
